RAM.v
module RAM(
    input clk,
    input wrEn,
    input [3:0] wrAddr,
    input [7:0] wrData,
    input [3:0] rdAddr,
    output reg [7:0] rdData
);
reg [7:0] mem[15:0];
always @(posedge clk) begin
    if(wrEn)
    mem[wrAddr]<=wrData;
end
always @(posedge clk) begin
    rdData<=mem[rdAddr];
end

endmodule

RAMtb.v
`timescale 1ps/1ps
`include "RAM.v"
module RAMtb();
reg clk,wrEn;
reg [3:0] rdAddr,wrAddr;
reg [7:0] wrData;
wire [7:0] rdData;
RAM DUT(
    .clk(clk),
    .wrEn(wrEn),
    .rdAddr(rdAddr),
    .rdData(rdData),
    .wrAddr(wrAddr),
    .wrData(wrData)
);
initial begin
  clk=1'b0;
//   rst=1'b1;
//   #15 rst=1'b0;

end
initial forever begin
    #5 clk=~clk;
end
initial begin
    $monitor("%t,wrEn=%b,wrAddr=%b,wrData=%b,rdAddr=%b,rdData=%b",$time,wrEn,wrAddr,wrData,rdAddr,rdData);
    $dumpfile("RAM.vcd");
    $dumpvars;
end
initial begin
    #15 wrEn=0;
    #10 wrEn=1;wrAddr=0;wrData=25;
    #10 wrEn=1;wrAddr=1;wrData=26;
    #10 wrEn=1;wrAddr=2;wrData=27;
    #10 wrEn=1;wrAddr=3;wrData=28;
    #10 wrEn=1;wrAddr=4;wrData=29;
    #10 wrEn=1;wrAddr=5;wrData=30;
    #10 wrEn=1;wrAddr=6;wrData=31;
    #10 wrEn=1;wrAddr=7;wrData=32;
    #10 wrEn=1;wrAddr=8;wrData=33;
    #10 wrEn=1;wrAddr=9;wrData=34;
    #10 wrEn=1;wrAddr=10;wrData=35;
    #10 wrEn=1;wrAddr=11;wrData=36;
    #10 wrEn=1;wrAddr=12;wrData=37;
    #10 wrEn=0;rdAddr=0;
    #10 wrEn=0;rdAddr=1;
    #10 wrEn=0;rdAddr=2;
    #10 wrEn=0;rdAddr=3;
    #10 wrEn=0;rdAddr=4;
    #10 wrEn=0;rdAddr=5;
    #10 wrEn=0;rdAddr=6;
    #10 wrEn=0;rdAddr=7;
    #10 wrEn=0;rdAddr=8;
    #10 wrEn=0;rdAddr=9;
    #10 wrEn=0;rdAddr=10;
    #10 wrEn=0;rdAddr=11;
    #10 wrEn=0;rdAddr=12;
    #20 $finish;
end
endmodule

RAM.vcd
$date
	Fri Aug 18 23:54:04 2023
$end
$version
	Icarus Verilog
$end
$timescale
	1ps
$end
$scope module RAMtb $end
$var wire 8 ! rdData [7:0] $end
$var reg 1 " clk $end
$var reg 4 # rdAddr [3:0] $end
$var reg 4 $ wrAddr [3:0] $end
$var reg 8 % wrData [7:0] $end
$var reg 1 & wrEn $end
$scope module DUT $end
$var wire 1 " clk $end
$var wire 4 ' rdAddr [3:0] $end
$var wire 4 ( wrAddr [3:0] $end
$var wire 8 ) wrData [7:0] $end
$var wire 1 & wrEn $end
$var reg 8 * rdData [7:0] $end
$upscope $end
$upscope $end
$enddefinitions $end
$comment Show the parameter values. $end
$dumpall
$end
#0
$dumpvars
bx *
bx )
bx (
bx '
x&
bx %
bx $
bx #
0"
bx !
$end
#5
1"
#10
0"
#15
1"
0&
#20
0"
#25
1"
b11001 %
b11001 )
b0 $
b0 (
1&
#30
0"
#35
1"
b11010 %
b11010 )
b1 $
b1 (
#40
0"
#45
1"
b11011 %
b11011 )
b10 $
b10 (
#50
0"
#55
1"
b11100 %
b11100 )
b11 $
b11 (
#60
0"
#65
1"
b11101 %
b11101 )
b100 $
b100 (
#70
0"
#75
1"
b11110 %
b11110 )
b101 $
b101 (
#80
0"
#85
1"
b11111 %
b11111 )
b110 $
b110 (
#90
0"
#95
1"
b100000 %
b100000 )
b111 $
b111 (
#100
0"
#105
1"
b100001 %
b100001 )
b1000 $
b1000 (
#110
0"
#115
1"
b100010 %
b100010 )
b1001 $
b1001 (
#120
0"
#125
1"
b100011 %
b100011 )
b1010 $
b1010 (
#130
0"
#135
1"
b100100 %
b100100 )
b1011 $
b1011 (
#140
0"
#145
1"
b100101 %
b100101 )
b1100 $
b1100 (
#150
0"
#155
b11001 !
b11001 *
1"
b0 #
b0 '
0&
#160
0"
#165
b11010 !
b11010 *
1"
b1 #
b1 '
#170
0"
#175
b11011 !
b11011 *
1"
b10 #
b10 '
#180
0"
#185
b11100 !
b11100 *
1"
b11 #
b11 '
#190
0"
#195
b11101 !
b11101 *
1"
b100 #
b100 '
#200
0"
#205
b11110 !
b11110 *
1"
b101 #
b101 '
#210
0"
#215
b11111 !
b11111 *
1"
b110 #
b110 '
#220
0"
#225
b100000 !
b100000 *
1"
b111 #
b111 '
#230
0"
#235
b100001 !
b100001 *
1"
b1000 #
b1000 '
#240
0"
#245
b100010 !
b100010 *
1"
b1001 #
b1001 '
#250
0"
#255
b100011 !
b100011 *
1"
b1010 #
b1010 '
#260
0"
#265
b100100 !
b100100 *
1"
b1011 #
b1011 '
#270
0"
#275
b100101 !
b100101 *
1"
b1100 #
b1100 '
